frostbyte/__init__.py
frostbyte/node.py
frostbyte_lang-0.0.0.dist-info/LICENSE
frostbyte_lang-0.0.0.dist-info/METADATA
frostbyte_lang-0.0.0.dist-info/WHEEL
frostbyte_lang-0.0.0.dist-info/entry_points.txt
frostbyte_lang-0.0.0.dist-info/top_level.txt
frostbyte_lang-0.0.0.dist-info/RECORD
