Metadata-Version: 2.1
Name: frostbyte-lang
Version: 0.0.0
Summary: Reference implementation for the Frostbyte programming language and smart contract protocol.
Home-page: https://github.com/frostbyte-lang/frostbyte-lang
Author: hashberg
Author-email: sg495@users.noreply.github.com
License: UNKNOWN
Platform: UNKNOWN
Classifier: Programming Language :: Python :: 3.9
Classifier: Operating System :: OS Independent
Classifier: Development Status :: 1 - Planning
Classifier: Natural Language :: English
Classifier: Typing :: Typed
Requires-Dist: cbor2
Requires-Dist: py-cid
